main.py
setup.py
Hybrid_SD.egg-info/PKG-INFO
Hybrid_SD.egg-info/SOURCES.txt
Hybrid_SD.egg-info/dependency_links.txt
Hybrid_SD.egg-info/requires.txt
Hybrid_SD.egg-info/top_level.txt